django_mdbook/__init__.py
django_mdbook/views.py
django_mdbook-0.2.0.dist-info/LICENSE.txt
django_mdbook-0.2.0.dist-info/METADATA
django_mdbook-0.2.0.dist-info/WHEEL
django_mdbook-0.2.0.dist-info/top_level.txt
django_mdbook-0.2.0.dist-info/RECORD
