Metadata-Version: 2.1
Name: django-mdbook
Version: 0.2.0
Summary: Provide a view for serving and updating books created with mdBook
Home-page: https://github.com/9999years/django-mdbook
Author: Rebecca Turner
Author-email: 637275@gmail.com
License: MIT License
Platform: UNKNOWN
Classifier: Environment :: Web Environment
Classifier: Framework :: Django
Classifier: Framework :: Django :: 2.0
Classifier: Intended Audience :: Developers
Classifier: License :: OSI Approved :: MIT License
Classifier: Operating System :: OS Independent
Classifier: Programming Language :: Python :: 3
Classifier: Topic :: Internet :: WWW/HTTP
Classifier: Topic :: Internet :: WWW/HTTP :: Dynamic Content
Classifier: Development Status :: 4 - Beta
Requires-Dist: django (~=2.0.0)
Requires-Dist: toml (~=0.10.0)
Requires-Dist: cached-property (~=1.5.0)
